clusterra/__init__.py
clusterra/api.py
clusterra/config.py
clusterra/main.py
clusterra/utils.py
clusterra/commands/__init__.py
clusterra/commands/auth.py
clusterra/commands/billing.py
clusterra/commands/clusters.py
clusterra/commands/jobs.py
clusterra_cli-0.1.2.dist-info/METADATA
clusterra_cli-0.1.2.dist-info/WHEEL
clusterra_cli-0.1.2.dist-info/entry_points.txt
clusterra_cli-0.1.2.dist-info/RECORD
