Metadata-Version: 2.4
Name: clusterra-cli
Version: 0.1.2
Summary: Command Line Interface for Clusterra HPC Management
Project-URL: Homepage, https://clusterra.io
Project-URL: Documentation, https://docs.clusterra.io
Project-URL: Repository, https://github.com/clusterra/clusterra
Author-email: Clusterra Engineering <engineering@clusterra.io>
License: MIT
Classifier: Development Status :: 4 - Beta
Classifier: Intended Audience :: Developers
Classifier: Intended Audience :: Science/Research
Classifier: Programming Language :: Python :: 3
Classifier: Programming Language :: Python :: 3.9
Classifier: Programming Language :: Python :: 3.10
Classifier: Programming Language :: Python :: 3.11
Classifier: Topic :: System :: Clustering
Requires-Python: >=3.9
Requires-Dist: fastapi
Requires-Dist: httpx
Requires-Dist: pydantic
Requires-Dist: rich
Requires-Dist: typer[all]
Requires-Dist: uvicorn
